cellrank/__init__.py
cellrank/datasets.py
cellrank/_utils/__init__.py
cellrank/_utils/_colors.py
cellrank/_utils/_docs.py
cellrank/_utils/_enum.py
cellrank/_utils/_key.py
cellrank/_utils/_lineage.py
cellrank/_utils/_linear_solver.py
cellrank/_utils/_parallelize.py
cellrank/_utils/_utils.py
cellrank/estimators/__init__.py
cellrank/estimators/_base_estimator.py
cellrank/estimators/mixins/__init__.py
cellrank/estimators/mixins/_fate_probabilities.py
cellrank/estimators/mixins/_kernel.py
cellrank/estimators/mixins/_lineage_drivers.py
cellrank/estimators/mixins/_utils.py
cellrank/estimators/mixins/decomposition/__init__.py
cellrank/estimators/mixins/decomposition/_eigen.py
cellrank/estimators/mixins/decomposition/_schur.py
cellrank/estimators/terminal_states/__init__.py
cellrank/estimators/terminal_states/_cflare.py
cellrank/estimators/terminal_states/_gpcca.py
cellrank/estimators/terminal_states/_term_states_estimator.py
cellrank/kernels/__init__.py
cellrank/kernels/_base_kernel.py
cellrank/kernels/_connectivity_kernel.py
cellrank/kernels/_cytotrace_kernel.py
cellrank/kernels/_experimental_time_kernel.py
cellrank/kernels/_precomputed_kernel.py
cellrank/kernels/_pseudotime_kernel.py
cellrank/kernels/_real_time_kernel.py
cellrank/kernels/_utils.py
cellrank/kernels/_velocity_kernel.py
cellrank/kernels/mixins/__init__.py
cellrank/kernels/mixins/_anndata.py
cellrank/kernels/mixins/_io.py
cellrank/kernels/mixins/_kernel.py
cellrank/kernels/utils/__init__.py
cellrank/kernels/utils/_projection.py
cellrank/kernels/utils/_pseudotime_scheme.py
cellrank/kernels/utils/_random_walk.py
cellrank/kernels/utils/_similarity.py
cellrank/kernels/utils/_tmat_flow.py
cellrank/kernels/utils/_velocity_model.py
cellrank/logging/__init__.py
cellrank/logging/_logging.py
cellrank/models/__init__.py
cellrank/models/_base_model.py
cellrank/models/_gamr_model.py
cellrank/models/_pygam_model.py
cellrank/models/_sklearn_model.py
cellrank/models/_utils.py
cellrank/pl/__init__.py
cellrank-2.0.7.dist-info/licenses/LICENSE
cellrank-2.0.7.dist-info/METADATA
cellrank-2.0.7.dist-info/WHEEL
cellrank-2.0.7.dist-info/top_level.txt
cellrank-2.0.7.dist-info/RECORD
