Metadata-Version: 2.4
Name: cellrank
Version: 2.0.7
Summary: CellRank: dynamics from multi-view single-cell data
Author: Marius Lange, Michal Klein, Philipp Weiler
Maintainer-email: Michal Klein <info@cellrank.org>
License-Expression: BSD-3-Clause
Project-URL: Homepage, https://github.com/theislab/cellrank
Project-URL: Download, https://cellrank.readthedocs.io/en/latest/installation.html
Project-URL: Bug Tracker, https://github.com/theislab/cellrank/issues
Project-URL: Documentation, https://cellrank.readthedocs.io
Project-URL: Source Code, https://github.com/theislab/cellrank
Keywords: single-cell,bio-informatics,RNA velocity,Markov chain,GPCCA
Classifier: Development Status :: 5 - Production/Stable
Classifier: Intended Audience :: Developers
Classifier: Intended Audience :: Science/Research
Classifier: Natural Language :: English
Classifier: Operating System :: POSIX :: Linux
Classifier: Operating System :: MacOS :: MacOS X
Classifier: Operating System :: Microsoft :: Windows
Classifier: Typing :: Typed
Classifier: Programming Language :: Python :: 3
Classifier: Programming Language :: Python :: 3.9
Classifier: Programming Language :: Python :: 3.10
Classifier: Programming Language :: Python :: 3.11
Classifier: Programming Language :: Python :: 3.12
Classifier: Topic :: Scientific/Engineering :: Bio-Informatics
Classifier: Topic :: Scientific/Engineering :: Mathematics
Classifier: Topic :: Scientific/Engineering :: Visualization
Requires-Python: >=3.9
License-File: LICENSE
Requires-Dist: anndata>=0.9
Requires-Dist: docrep>=0.3.0
Requires-Dist: joblib>=0.13.1
Requires-Dist: matplotlib>=3.5.0
Requires-Dist: networkx>=2.2
Requires-Dist: numba!=0.57.0,>=0.51.0
Requires-Dist: numpy>=1.22.0
Requires-Dist: pandas>=1.5.0
Requires-Dist: pygam>=0.8.0
Requires-Dist: pygpcca>=1.0.4
Requires-Dist: scanpy>=1.7.2
Requires-Dist: scikit-learn>=0.24.0
Requires-Dist: scipy>=1.12.0
Requires-Dist: scvelo>=0.2.5
Requires-Dist: seaborn>=0.10.0
Requires-Dist: wrapt>=1.12.1
Provides-Extra: dev
Requires-Dist: pre-commit>=3.0.0; extra == "dev"
Requires-Dist: tox>=4; extra == "dev"
Provides-Extra: test
Requires-Dist: pytest>=8; extra == "test"
Requires-Dist: pytest-mock>=3.5.0; extra == "test"
Requires-Dist: pytest-cov>=4; extra == "test"
Requires-Dist: pytest-xdist; extra == "test"
Requires-Dist: coverage[toml]>=7; extra == "test"
Requires-Dist: zarr<3; extra == "test"
Requires-Dist: igraph; extra == "test"
Requires-Dist: leidenalg; extra == "test"
Requires-Dist: Pillow; extra == "test"
Requires-Dist: jax; extra == "test"
Provides-Extra: docs
Requires-Dist: sphinx>=5.1.1; extra == "docs"
Requires-Dist: furo>=2022.09.29; extra == "docs"
Requires-Dist: myst-nb>=0.17.1; extra == "docs"
Requires-Dist: sphinx-tippy>=0.4.1; extra == "docs"
Requires-Dist: sphinx-autodoc-typehints>=1.10.3; extra == "docs"
Requires-Dist: sphinx_copybutton>=0.5.0; extra == "docs"
Requires-Dist: sphinx_design>=0.3.0; extra == "docs"
Requires-Dist: sphinxcontrib-bibtex>=2.3.0; extra == "docs"
Requires-Dist: sphinxcontrib-spelling>=7.6.2; extra == "docs"
Dynamic: license-file
